TEScal-0.3.0.dist-info/METADATA
TEScal-0.3.0.dist-info/RECORD
TEScal-0.3.0.dist-info/WHEEL
TEScal-0.3.0.dist-info/top_level.txt
tescal/__init__.py
tescal/detcal/__init__.py
tescal/detcal/cut.py
tescal/detcal/didv.py
tescal/detcal/iv.py
tescal/detcal/noise.py
tescal/detcal/sim.py
tescal/fitting/__init__.py
tescal/fitting/fitting.py
tescal/io/__init__.py
tescal/io/io.py
tescal/plotting/__init__.py
tescal/plotting/plotting.py
tescal/trigger/__init__.py
tescal/trigger/cont_trigger.py
tescal/utils/__init__.py
tescal/utils/utils.py
