Metadata-Version: 2.1
Name: TEScal
Version: 0.3.0
Summary: TES detector calibration Python Tools
Home-page: https://github.com/berkeleycdms/TEScal
Author: Samuel Watkins, Caleb Fink
Author-email: samwatkins@berkeley.edu, cwfink@berkeley.edu
License: UNKNOWN
Platform: UNKNOWN
